DirectGuiExtension/DirectAutoSizer.py
DirectGuiExtension/DirectBoxSizer.py
DirectGuiExtension/DirectCollapsibleFrame.py
DirectGuiExtension/DirectDatePicker.py
DirectGuiExtension/DirectDiagram.py
DirectGuiExtension/DirectGridSizer.py
DirectGuiExtension/DirectGuiHelper.py
DirectGuiExtension/DirectMenuItem.py
DirectGuiExtension/DirectOptionMenu.py
DirectGuiExtension/DirectScrolledWindowFrame.py
DirectGuiExtension/DirectSpinBox.py
DirectGuiExtension/DirectSplitFrame.py
DirectGuiExtension/DirectTabbedFrame.py
DirectGuiExtension/DirectTooltip.py
DirectGuiExtension/__init__.py
DirectGuiExtension-22.9.dist-info/LICENSE
DirectGuiExtension-22.9.dist-info/METADATA
DirectGuiExtension-22.9.dist-info/WHEEL
DirectGuiExtension-22.9.dist-info/top_level.txt
DirectGuiExtension-22.9.dist-info/RECORD
