Metadata-Version: 2.1
Name: DirectGuiExtension
Version: 22.9
Summary: A set of extensions for the DirectGUI system of the Panda3D engine
Home-page: https://github.com/fireclawthefox/DirectGuiExtension
Author: Fireclaw
Author-email: fireclawthefox@gmail.com
Project-URL: Documentation, https://github.com/fireclawthefox/DirectGuiExtension/wiki
Classifier: Programming Language :: Python :: 3
Classifier: License :: OSI Approved :: BSD License
Classifier: Operating System :: OS Independent
Classifier: Development Status :: 3 - Alpha
Classifier: Intended Audience :: Developers
Classifier: Intended Audience :: End Users/Desktop
Classifier: Topic :: Software Development :: User Interfaces
Requires-Python: >=3.6
License-File: LICENSE
Requires-Dist: panda3d
